LICENSE
MANIFEST.in
README.md
setup.py
HQDataAPIWrapper/__init__.py
HQDataAPIWrapper/main.py
hqdata_api_wrapper.egg-info/PKG-INFO
hqdata_api_wrapper.egg-info/SOURCES.txt
hqdata_api_wrapper.egg-info/dependency_links.txt
hqdata_api_wrapper.egg-info/requires.txt
hqdata_api_wrapper.egg-info/top_level.txt