Metadata-Version: 2.1
Name: hqdata_api_wrapper
Version: 0.0.3
Summary: A Python wrapper for the HQData API
Home-page: https://hqdata.com
Author: Marco Capuano
Author-email: marco.capuano@starux.ch
License-File: LICENSE
Requires-Dist: requests
